{
  "prefab": "C:\\Users\\jaspe\\WebstormProjects\\farever\\out\\Character\\Hero\\Outfit\\Faction\\Swarowls\\Variation\\XSwarowls_02\\Chest_LongSleeves_XSwarowls_02_Light.prefab",
  "assetRoot": "C:\\Users\\jaspe\\WebstormProjects\\farever\\out",
  "modelSource": "Character/Hero/Outfit/Faction/Swarowls/Sources/Chest_RSwarowls_Light_N.fbx",
  "modelResolvedSource": "C:\\Users\\jaspe\\WebstormProjects\\farever\\out\\Character\\Hero\\Outfit\\Faction\\Swarowls\\Sources\\Chest_RSwarowls_Light_N.fbx",
  "hmdMaterials": [
    {
      "index": 0,
      "name": "GradMat_Body",
      "diffuseTexture": "Character/Common/Texture/CustomGradient_RobinHoof.png",
      "diffuseResolved": "C:\\Users\\jaspe\\WebstormProjects\\farever\\out\\Character\\Common\\Texture\\CustomGradient_RobinHoof.png",
      "specularTexture": null,
      "specularResolved": null,
      "normalMap": null,
      "normalResolved": null,
      "diffuseOut": "textures/Character/Common/Texture/CustomGradient_RobinHoof.png",
      "specularOut": null,
      "normalOut": null
    }
  ],
  "gradMat": {
    "name": "gradmat",
    "slots": [
      "Skin_00",
      "Leather_02b",
      "Leather_09b",
      "PurpleGrey_01",
      "Beige_04",
      "BlueGreen_02",
      "Leather_05",
      "Gold_03",
      "Black_Warm_02",
      "Beige_02",
      "Bone_01",
      "Black_Warm_02"
    ],
    "numSlots": 12,
    "resolvedSlots": [
      {
        "id": "Skin_00",
        "texture": "Character/Common/Texture/Gradient/Skin_00.png",
        "resolvedTexture": "C:\\Users\\jaspe\\WebstormProjects\\farever\\out\\Character\\Common\\Texture\\Gradient\\Skin_00.png",
        "source": "data.cdb",
        "cdbRef": {
          "file": "Character/Common/Texture/Gradient/Skin_00.png",
          "size": 8,
          "x": 0,
          "y": 7
        },
        "bodyParts": 0,
        "playerCustomization": false,
        "out": "textures/Character/Common/Texture/Gradient/Skin_00.png"
      },
      {
        "id": "Leather_02b",
        "texture": "Character/Common/Texture/Gradient/Leather_02b.png",
        "resolvedTexture": "C:\\Users\\jaspe\\WebstormProjects\\farever\\out\\Character\\Common\\Texture\\Gradient\\Leather_02b.png",
        "source": "data.cdb",
        "cdbRef": {
          "file": "Character/Common/Texture/Gradient/Leather_02b.png",
          "size": 32,
          "x": 0,
          "y": 3
        },
        "bodyParts": 0,
        "playerCustomization": false,
        "out": "textures/Character/Common/Texture/Gradient/Leather_02b.png"
      },
      {
        "id": "Leather_09b",
        "texture": "Character/Common/Texture/Gradient/Leather_09b.png",
        "resolvedTexture": "C:\\Users\\jaspe\\WebstormProjects\\farever\\out\\Character\\Common\\Texture\\Gradient\\Leather_09b.png",
        "source": "data.cdb",
        "cdbRef": {
          "file": "Character/Common/Texture/Gradient/Leather_09b.png",
          "size": 32,
          "x": 0,
          "y": 4
        },
        "bodyParts": 2,
        "playerCustomization": true,
        "out": "textures/Character/Common/Texture/Gradient/Leather_09b.png"
      },
      {
        "id": "PurpleGrey_01",
        "texture": "Character/Common/Texture/Gradient/Fabric_PurpleGrey_01.png",
        "resolvedTexture": "C:\\Users\\jaspe\\WebstormProjects\\farever\\out\\Character\\Common\\Texture\\Gradient\\Fabric_PurpleGrey_01.png",
        "source": "data.cdb",
        "cdbRef": {
          "file": "Character/Common/Texture/Gradient/Fabric_PurpleGrey_01.png",
          "size": 32,
          "x": 0,
          "y": 3
        },
        "bodyParts": 0,
        "playerCustomization": false,
        "out": "textures/Character/Common/Texture/Gradient/Fabric_PurpleGrey_01.png"
      },
      {
        "id": "Beige_04",
        "texture": "Character/Common/Texture/Gradient/Fabric_Beige_04.png",
        "resolvedTexture": "C:\\Users\\jaspe\\WebstormProjects\\farever\\out\\Character\\Common\\Texture\\Gradient\\Fabric_Beige_04.png",
        "source": "data.cdb",
        "cdbRef": {
          "file": "Character/Common/Texture/Gradient/Fabric_Beige_04.png",
          "size": 32,
          "x": 0,
          "y": 3
        },
        "bodyParts": 0,
        "playerCustomization": false,
        "out": "textures/Character/Common/Texture/Gradient/Fabric_Beige_04.png"
      },
      {
        "id": "BlueGreen_02",
        "texture": "Character/Common/Texture/Gradient/Fabric_BlueGreen_02.png",
        "resolvedTexture": "C:\\Users\\jaspe\\WebstormProjects\\farever\\out\\Character\\Common\\Texture\\Gradient\\Fabric_BlueGreen_02.png",
        "source": "data.cdb",
        "cdbRef": {
          "file": "Character/Common/Texture/Gradient/Fabric_BlueGreen_02.png",
          "size": 32,
          "x": 0,
          "y": 2
        },
        "bodyParts": 2,
        "playerCustomization": true,
        "out": "textures/Character/Common/Texture/Gradient/Fabric_BlueGreen_02.png"
      },
      {
        "id": "Leather_05",
        "texture": "Character/Common/Texture/Gradient/Leather_05.png",
        "resolvedTexture": "C:\\Users\\jaspe\\WebstormProjects\\farever\\out\\Character\\Common\\Texture\\Gradient\\Leather_05.png",
        "source": "data.cdb",
        "cdbRef": {
          "file": "Character/Common/Texture/Gradient/Leather_05.png",
          "size": 32,
          "x": 0,
          "y": 3
        },
        "bodyParts": 2,
        "playerCustomization": true,
        "out": "textures/Character/Common/Texture/Gradient/Leather_05.png"
      },
      {
        "id": "Gold_03",
        "texture": "Character/Common/Texture/Gradient/Gold_03.png",
        "resolvedTexture": "C:\\Users\\jaspe\\WebstormProjects\\farever\\out\\Character\\Common\\Texture\\Gradient\\Gold_03.png",
        "source": "data.cdb",
        "cdbRef": {
          "file": "Character/Common/Texture/Gradient/Gold_03.png",
          "size": 32,
          "x": 0,
          "y": 3
        },
        "bodyParts": 0,
        "playerCustomization": false,
        "out": "textures/Character/Common/Texture/Gradient/Gold_03.png"
      },
      {
        "id": "Black_Warm_02",
        "texture": "Character/Common/Texture/Gradient/Fabric_Black_Warm_02.png",
        "resolvedTexture": "C:\\Users\\jaspe\\WebstormProjects\\farever\\out\\Character\\Common\\Texture\\Gradient\\Fabric_Black_Warm_02.png",
        "source": "data.cdb",
        "cdbRef": {
          "file": "Character/Common/Texture/Gradient/Fabric_Black_Warm_02.png",
          "size": 32,
          "x": 0,
          "y": 3
        },
        "bodyParts": 0,
        "playerCustomization": false,
        "out": "textures/Character/Common/Texture/Gradient/Fabric_Black_Warm_02.png"
      },
      {
        "id": "Beige_02",
        "texture": "Character/Common/Texture/Gradient/Fabric_Beige_02.png",
        "resolvedTexture": "C:\\Users\\jaspe\\WebstormProjects\\farever\\out\\Character\\Common\\Texture\\Gradient\\Fabric_Beige_02.png",
        "source": "data.cdb",
        "cdbRef": {
          "file": "Character/Common/Texture/Gradient/Fabric_Beige_02.png",
          "size": 32,
          "x": 0,
          "y": 3
        },
        "bodyParts": 0,
        "playerCustomization": false,
        "out": "textures/Character/Common/Texture/Gradient/Fabric_Beige_02.png"
      },
      {
        "id": "Bone_01",
        "texture": "Character/Common/Texture/Gradient/Bone_01.png",
        "resolvedTexture": "C:\\Users\\jaspe\\WebstormProjects\\farever\\out\\Character\\Common\\Texture\\Gradient\\Bone_01.png",
        "source": "data.cdb",
        "cdbRef": {
          "file": "Character/Common/Texture/Gradient/Bone_01.png",
          "size": 32,
          "x": 0,
          "y": 3
        },
        "bodyParts": 0,
        "playerCustomization": false,
        "out": "textures/Character/Common/Texture/Gradient/Bone_01.png"
      },
      {
        "id": "Black_Warm_02",
        "texture": "Character/Common/Texture/Gradient/Fabric_Black_Warm_02.png",
        "resolvedTexture": "C:\\Users\\jaspe\\WebstormProjects\\farever\\out\\Character\\Common\\Texture\\Gradient\\Fabric_Black_Warm_02.png",
        "source": "data.cdb",
        "cdbRef": {
          "file": "Character/Common/Texture/Gradient/Fabric_Black_Warm_02.png",
          "size": 32,
          "x": 0,
          "y": 3
        },
        "bodyParts": 0,
        "playerCustomization": false,
        "out": "textures/Character/Common/Texture/Gradient/Fabric_Black_Warm_02.png"
      }
    ],
    "linesTex": "Character/Common/Texture/UV_Lines.png",
    "linesTexResolved": "C:\\Users\\jaspe\\WebstormProjects\\farever\\out\\Character\\Common\\Texture\\UV_Lines.png",
    "patternPath": "Character/Common/Texture/Pattern/Pattern_Braid03.png",
    "patternResolved": "C:\\Users\\jaspe\\WebstormProjects\\farever\\out\\Character\\Common\\Texture\\Pattern\\Pattern_Braid03.png",
    "patternAlphaPath": null,
    "patternAlphaResolved": null,
    "marks": [
      null,
      null,
      null,
      null
    ],
    "marksResolved": [
      null,
      null,
      null,
      null
    ],
    "outlineSize": 0,
    "outlineIntensity": 1,
    "linesBlend": 1,
    "minLightPower": 0,
    "shadowSmooth": 0.1,
    "lightSmooth": 0.1,
    "terminatorSize": 0.5,
    "shadowBias": 0,
    "specSize": 0.8,
    "specInsideSize": 0.5,
    "specInsideIntensity": 0,
    "specSmooth": 0.05,
    "specAlpha": 1,
    "emissivePow": 0,
    "rimLightAngle": 0,
    "rimLightWidth": 1,
    "rimLightSize": 0,
    "rimLightSmooth": 0.05,
    "rimLightMin": 0,
    "rimLightSpecMultiplier": 0,
    "rimLightColor": [
      1,
      1,
      1
    ],
    "ambientColor": [
      1,
      1,
      1
    ],
    "ambientIntensity": 0,
    "useVertexColor": true,
    "linesOut": "textures/Character/Common/Texture/UV_Lines.png",
    "patternOut": "textures/Character/Common/Texture/Pattern/Pattern_Braid03.png",
    "patternAlphaOut": null,
    "marksOut": [
      null,
      null,
      null,
      null
    ]
  },
  "cdb": "C:\\Users\\jaspe\\WebstormProjects\\farever\\out\\data.cdb",
  "warnings": []
}